.class public myClass
.super java/lang/Object

.method public <init>()V
        aload_0
        invokespecial java/lang/Object.<init>()V
        return
.end method

.method public sum([I[I)[I
        .limit stack 4
        .limit locals 12
        aload 1
        arraylength
        istore 3
iload 3
        newarray int
        astore 4
        iconst_0
        istore 6
Loop1:
        aload 1
        arraylength
        istore 7
        iload 6
        iload 7
        if_icmplt Body1
        goto EndLoop1
Body1:
        iload 6
        istore 8
        aload 1
        iload 8
        iaload
        istore 9
        iload 6
        istore 10
        aload 2
        iload 10
        iaload
        istore 11
        aload 4
        iload 6
        iload 9
        iload 11
        iadd
        iastore
        iload 6
        iinc 6 1
        goto Loop1
EndLoop1:
        aload 4
        areturn
.end method
